audio_upscaler/__init__.py
audio_upscaler/lowpass.py
audio_upscaler/pipeline.py
audio_upscaler/predict.py
audio_upscaler/utils.py
audio_upscaler/clap/__init__.py
audio_upscaler/clap/open_clip/__init__.py
audio_upscaler/clap/open_clip/bpe_simple_vocab_16e6.txt.gz
audio_upscaler/clap/open_clip/factory.py
audio_upscaler/clap/open_clip/feature_fusion.py
audio_upscaler/clap/open_clip/htsat.py
audio_upscaler/clap/open_clip/loss.py
audio_upscaler/clap/open_clip/model.py
audio_upscaler/clap/open_clip/openai.py
audio_upscaler/clap/open_clip/pann_model.py
audio_upscaler/clap/open_clip/pretrained.py
audio_upscaler/clap/open_clip/timm_model.py
audio_upscaler/clap/open_clip/tokenizer.py
audio_upscaler/clap/open_clip/transform.py
audio_upscaler/clap/open_clip/utils.py
audio_upscaler/clap/open_clip/model_configs/HTSAT-base.json
audio_upscaler/clap/open_clip/model_configs/HTSAT-large.json
audio_upscaler/clap/open_clip/model_configs/HTSAT-tiny-win-1536.json
audio_upscaler/clap/open_clip/model_configs/HTSAT-tiny.json
audio_upscaler/clap/open_clip/model_configs/PANN-10.json
audio_upscaler/clap/open_clip/model_configs/PANN-14-fmax-18k.json
audio_upscaler/clap/open_clip/model_configs/PANN-14-fmax-8k-20s.json
audio_upscaler/clap/open_clip/model_configs/PANN-14-tiny-transformer.json
audio_upscaler/clap/open_clip/model_configs/PANN-14-win-1536.json
audio_upscaler/clap/open_clip/model_configs/PANN-14.json
audio_upscaler/clap/open_clip/model_configs/PANN-6.json
audio_upscaler/clap/open_clip/model_configs/RN101-quickgelu.json
audio_upscaler/clap/open_clip/model_configs/RN101.json
audio_upscaler/clap/open_clip/model_configs/RN50-quickgelu.json
audio_upscaler/clap/open_clip/model_configs/RN50.json
audio_upscaler/clap/open_clip/model_configs/RN50x16.json
audio_upscaler/clap/open_clip/model_configs/RN50x4.json
audio_upscaler/clap/open_clip/model_configs/ViT-B-16.json
audio_upscaler/clap/open_clip/model_configs/ViT-B-32-quickgelu.json
audio_upscaler/clap/open_clip/model_configs/ViT-B-32.json
versatile_audio_upscaler-0.0.2.dist-info/LICENSE
versatile_audio_upscaler-0.0.2.dist-info/METADATA
versatile_audio_upscaler-0.0.2.dist-info/WHEEL
versatile_audio_upscaler-0.0.2.dist-info/top_level.txt
versatile_audio_upscaler-0.0.2.dist-info/RECORD
