Metadata-Version: 2.1
Name: versatile-audio-upscaler
Version: 0.0.2
Summary: Versatile AI-driven audio upscaler to enhance the quality of any audio.
Home-page: https://github.com/IAHispano/Audio-Upscaler
Author: Pascal Aznar
Author-email: blaise@applio.org
License: MIT
Platform: UNKNOWN
Classifier: License :: OSI Approved :: MIT License
Classifier: Programming Language :: Python
Classifier: Programming Language :: Python :: 3
Classifier: Programming Language :: Python :: 3.7
Classifier: Programming Language :: Python :: Implementation :: CPython
Classifier: Programming Language :: Python :: Implementation :: PyPy
Requires-Python: >=3.7.0
License-File: LICENSE
Requires-Dist: torch>=1.13.0
Requires-Dist: torchaudio>=0.13.0
Requires-Dist: torchvision>=0.14.0
Requires-Dist: tqdm
Requires-Dist: pyyaml
Requires-Dist: einops
Requires-Dist: chardet
Requires-Dist: numpy<=1.23.5
Requires-Dist: soundfile
Requires-Dist: librosa==0.9.2
Requires-Dist: scipy
Requires-Dist: pandas
Requires-Dist: tokenizers>=0.14.1
Requires-Dist: unidecode
Requires-Dist: phonemizer
Requires-Dist: torchlibrosa>=0.0.9
Requires-Dist: transformers
Requires-Dist: wget
Requires-Dist: progressbar
Requires-Dist: ftfy
Requires-Dist: timm
Requires-Dist: matplotlib
